plone.behavior-2.0.3-py3.13-nspkg.pth
plone/behavior/__init__.py
plone/behavior/annotation.py
plone/behavior/annotation.rst
plone/behavior/behaviors.rst
plone/behavior/configure.zcml
plone/behavior/directives.rst
plone/behavior/factory.py
plone/behavior/interfaces.py
plone/behavior/markers.py
plone/behavior/meta.zcml
plone/behavior/metaconfigure.py
plone/behavior/registration.py
plone/behavior/tests.py
plone/behavior/vocab.py
plone_behavior-2.0.3.dist-info/METADATA
plone_behavior-2.0.3.dist-info/WHEEL
plone_behavior-2.0.3.dist-info/namespace_packages.txt
plone_behavior-2.0.3.dist-info/top_level.txt
plone_behavior-2.0.3.dist-info/RECORD
