Metadata-Version: 2.4
Name: plone.behavior
Version: 2.0.3
Summary: Infrastructure for maintaining a registry of available behaviors
Home-page: https://github.com/plone/plone.behavior
Author: Martin Aspeli
Author-email: optilude@gmail.com
Maintainer: Plone Foundation - Release Team
Maintainer-email: releaseteam@plone.org
License: BSD
Keywords: Plone behavior registry
Classifier: Development Status :: 6 - Mature
Classifier: Framework :: Plone
Classifier: Framework :: Plone :: 6.0
Classifier: Framework :: Plone :: Core
Classifier: Programming Language :: Python
Classifier: Programming Language :: Python :: 3.8
Classifier: Programming Language :: Python :: 3.9
Classifier: Programming Language :: Python :: 3.10
Classifier: Programming Language :: Python :: 3.11
Classifier: Topic :: Software Development :: Libraries :: Python Modules
Classifier: License :: OSI Approved :: BSD License
Requires-Python: >=3.8
Requires-Dist: setuptools
Requires-Dist: zope.annotation
Requires-Dist: zope.component
Requires-Dist: zope.configuration
Requires-Dist: zope.interface
Requires-Dist: zope.schema
Provides-Extra: test
Requires-Dist: zope.lifecycleevent; extra == "test"
Dynamic: author
Dynamic: author-email
Dynamic: classifier
Dynamic: description
Dynamic: description-content-type
Dynamic: home-page
Dynamic: keywords
Dynamic: license
Dynamic: maintainer
Dynamic: maintainer-email
Dynamic: provides-extra
Dynamic: requires-dist
Dynamic: requires-python
Dynamic: summary
